Beaconet/__init__.py
Beaconet/metrics/__init__.py
Beaconet/metrics/compute_PME.py
Beaconet/metrics/show.py
Beaconet/model/__init__.py
Beaconet/model/model.py
Beaconet-1.0.9.dist-info/LICENSE
Beaconet-1.0.9.dist-info/METADATA
Beaconet-1.0.9.dist-info/WHEEL
Beaconet-1.0.9.dist-info/top_level.txt
Beaconet-1.0.9.dist-info/RECORD
